qrwifi/__init__.py
qrwifi/__main__.py
qrwifi-0.1.1.dist-info/entry_points.txt
qrwifi-0.1.1.dist-info/WHEEL
qrwifi-0.1.1.dist-info/METADATA
qrwifi-0.1.1.dist-info/RECORD
